DSBplot/__init__.py
DSBplot/__main__.py
DSBplot/concat.py
DSBplot/graph.py
DSBplot/histogram.py
DSBplot/process.py
DSBplot/lib_graph/__init__.py
DSBplot/lib_graph/plot_graph.py
DSBplot/lib_graph/plot_graph_helper.py
DSBplot/lib_histogram/__init__.py
DSBplot/lib_histogram/plot_histogram.py
DSBplot/lib_process/__init__.py
DSBplot/lib_process/alignment_window.py
DSBplot/lib_process/filter_reads.py
DSBplot/lib_process/get_variation.py
DSBplot/lib_process/get_window.py
DSBplot/utils/__init__.py
DSBplot/utils/alignment_utils.py
DSBplot/utils/cigar_utils.py
DSBplot/utils/common_utils.py
DSBplot/utils/constants.py
DSBplot/utils/file_names.py
DSBplot/utils/file_utils.py
DSBplot/utils/graph_utils.py
DSBplot/utils/kmer_utils.py
DSBplot/utils/log_utils.py
DSBplot/utils/sam_utils.py
DSBplot-0.1.3.dist-info/LICENSE
DSBplot-0.1.3.dist-info/METADATA
DSBplot-0.1.3.dist-info/WHEEL
DSBplot-0.1.3.dist-info/entry_points.txt
DSBplot-0.1.3.dist-info/top_level.txt
DSBplot-0.1.3.dist-info/RECORD
