Metadata-Version: 2.1
Name: DSBplot
Version: 0.1.3
Summary: A package for visualizing alignment variations in DNA-seq data from double-strand break (DSB) experiments.
Author-email: Tejasvi Channagiri <tchannagiri@gmail.com>
Project-URL: Homepage, https://github.com/tchannagiri/DSBplot
Project-URL: Bug Tracker, https://github.com/tchannagiri/DSBplot/issues
Keywords: visualization,genomics,DNA-seq,DSB,double-strand break,alignment,graph,histogram
Classifier: Programming Language :: Python :: 3
Classifier: License :: OSI Approved :: MIT License
Classifier: Operating System :: OS Independent
Requires-Python: >=3.7
License-File: LICENSE
Requires-Dist: Levenshtein
Requires-Dist: matplotlib
Requires-Dist: networkx
Requires-Dist: numpy
Requires-Dist: pandas
Requires-Dist: Pillow
Requires-Dist: plotly
Requires-Dist: scikit-learn
